buyyoutubviewsnumtowords/__init__.py
buyyoutubviewsnumtowords/main.py
numtowords-0.0.1.dist-info/METADATA
numtowords-0.0.1.dist-info/WHEEL
numtowords-0.0.1.dist-info/top_level.txt
numtowords-0.0.1.dist-info/RECORD
