Metadata-Version: 2.1
Name: numtowords
Version: 0.0.1
Summary: number to words converter
Home-page: https://buyyoutubviews.com
Author: buy youtube views
Author-email: buyyoutubviews@gamil.com
Project-URL: Bug Tracker, https://buyyoutubviews.com
Classifier: Programming Language :: Python :: 3
Classifier: License :: OSI Approved :: MIT License
Classifier: Operating System :: OS Independent
Requires-Python: >=3.6
